aspose/__init__.py
aspose/pycore.cpython-310-darwin.so
aspose/pycore.cpython-311-darwin.so
aspose/pycore.cpython-312-darwin.so
aspose/pycore.cpython-313-darwin.so
aspose/pycore.cpython-35m-darwin.so
aspose/pycore.cpython-36m-darwin.so
aspose/pycore.cpython-37m-darwin.so
aspose/pycore.cpython-38-darwin.so
aspose/pycore.cpython-39-darwin.so
aspose/pygc.cpython-310-darwin.so
aspose/pygc.cpython-311-darwin.so
aspose/pygc.cpython-312-darwin.so
aspose/pygc.cpython-313-darwin.so
aspose/pygc.cpython-35m-darwin.so
aspose/pygc.cpython-36m-darwin.so
aspose/pygc.cpython-37m-darwin.so
aspose/pygc.cpython-38-darwin.so
aspose/pygc.cpython-39-darwin.so
aspose/pyreflection.cpython-310-darwin.so
aspose/pyreflection.cpython-311-darwin.so
aspose/pyreflection.cpython-312-darwin.so
aspose/pyreflection.cpython-313-darwin.so
aspose/pyreflection.cpython-35m-darwin.so
aspose/pyreflection.cpython-36m-darwin.so
aspose/pyreflection.cpython-37m-darwin.so
aspose/pyreflection.cpython-38-darwin.so
aspose/pyreflection.cpython-39-darwin.so
aspose/zip.cpython-310-darwin.so
aspose/zip.cpython-311-darwin.so
aspose/zip.cpython-312-darwin.so
aspose/zip.cpython-313-darwin.so
aspose/zip.cpython-35m-darwin.so
aspose/zip.cpython-36m-darwin.so
aspose/zip.cpython-37m-darwin.so
aspose/zip.cpython-38-darwin.so
aspose/zip.cpython-39-darwin.so
aspose/__pyinstaller/__init__.pyi
aspose/__pyinstaller/hook-aspose.py
aspose/assemblies/pycore/WrpInterop.Aspose.PyCore.dll
aspose/assemblies/pygc/Aspose.PyGC.dll
aspose/assemblies/pyreflection/WrpInterop.Aspose.PyReflection.dll
aspose/assemblies/zip/Aspose.Zip.dll
aspose/assemblies/zip/WrpInterop.Aspose.Zip.dll
aspose/netcore/netcore3.1/Microsoft.CSharp.dll
aspose/netcore/netcore3.1/Microsoft.VisualBasic.Core.dll
aspose/netcore/netcore3.1/Microsoft.VisualBasic.dll
aspose/netcore/netcore3.1/Microsoft.Win32.Primitives.dll
aspose/netcore/netcore3.1/Microsoft.Win32.Registry.dll
aspose/netcore/netcore3.1/SOS_README.md
aspose/netcore/netcore3.1/System.AppContext.dll
aspose_zip-26.1.0.dist-info/METADATA
aspose_zip-26.1.0.dist-info/WHEEL
aspose_zip-26.1.0.dist-info/entry_points.txt
aspose_zip-26.1.0.dist-info/top_level.txt
aspose_zip-26.1.0.dist-info/RECORD
