Metadata-Version: 2.1
Name: aspose-zip
Version: 26.1.0
Summary: Aspose.Zip for Python via .NET is a library that can be used by Python developers for a variety of archive-processing tasks. It supports ZIP, GZIP, BZIP2, TAR, CPIO, LZIP, 7Z, LZMA, XZ and Z formats. It allows you to encrypt and decrypt files, create self-extracting archives and extract RAR, CAB, WIM formats as well. The API is easy to use and robust.
Home-page: https://products.aspose.com/zip/python-net
Author: Aspose
License: Other/Proprietary License
Keywords: Zip, compression, decompression, encryption, decryption, deflate, sfx, self-extracted, self-extractor, pack, unpack, compress, decompress, encrypt, decrypt, extract,ZipCrypto, bzip2, PPMd, cpio, tar, untar, gnu-tar, shar, gzip, lzip, LZMA, 7z, LZMA2, RAR, RAR4, RAR5, cab, wim, xar, xz, snappy, Z
Platform: macos_x86_64
Classifier: Operating System :: Microsoft :: Windows
Classifier: Operating System :: POSIX :: Linux
Classifier: Operating System :: Unix
Classifier: Operating System :: MacOS
Classifier: License :: Other/Proprietary License
Classifier: Programming Language :: C#
Classifier: Programming Language :: Python :: 3
Classifier: Programming Language :: Python :: 3 :: Only
Classifier: Programming Language :: Python :: 3.5
Classifier: Programming Language :: Python :: 3.6
Classifier: Programming Language :: Python :: 3.7
Classifier: Programming Language :: Python :: 3.8
Classifier: Programming Language :: Python :: 3.9
Classifier: Programming Language :: Python :: 3.10
Classifier: Programming Language :: Python :: 3.11
Classifier: Programming Language :: Python :: 3.12
Classifier: Programming Language :: Python :: 3.13
Classifier: Development Status :: 5 - Production/Stable
Classifier: Topic :: Utilities
Classifier: Topic :: System :: Archiving
Classifier: Topic :: System :: Archiving :: Compression
Classifier: Topic :: System :: Archiving :: Packaging
Requires-Python: >=3.5,<3.14
